{
  "id": "2679624",
  "name": "AcousticPlatform",
  "font_family": "iconfont",
  "css_prefix_text": "icon-",
  "description": "基站平台",
  "glyphs": [
    {
      "icon_id": "7677927",
      "name": "场地",
      "font_class": "changdi",
      "unicode": "e614",
      "unicode_decimal": 58900
    },
    {
      "icon_id": "400824",
      "name": "history",
      "font_class": "history",
      "unicode": "e748",
      "unicode_decimal": 59208
    },
    {
      "icon_id": "20387655",
      "name": "data",
      "font_class": "data",
      "unicode": "e601",
      "unicode_decimal": 58881
    },
    {
      "icon_id": "11538093",
      "name": "local",
      "font_class": "local",
      "unicode": "e67d",
      "unicode_decimal": 59005
    },
    {
      "icon_id": "21489489",
      "name": "line-base station（基站）",
      "font_class": "line-basestationjizhan",
      "unicode": "e717",
      "unicode_decimal": 59159
    },
    {
      "icon_id": "19494228",
      "name": "声音",
      "font_class": "shengyin",
      "unicode": "e615",
      "unicode_decimal": 58901
    }
  ]
}
